MANIFEST.in
README.md
setup.py
ConsultaCNPJ/CNPJs.py
ConsultaCNPJ/__init__.py
ConsultaCNPJ/consulta_cnpj_prompt.py
ConsultaCNPJ.egg-info/PKG-INFO
ConsultaCNPJ.egg-info/SOURCES.txt
ConsultaCNPJ.egg-info/dependency_links.txt
ConsultaCNPJ.egg-info/not-zip-safe
ConsultaCNPJ.egg-info/requires.txt
ConsultaCNPJ.egg-info/top_level.txt
ConsultaCNPJ/tests/__init__.py
ConsultaCNPJ/tests/test_consulta_cnpj_prompt.py