Metadata-Version: 2.1
Name: ConsultaCNPJ
Version: 0.2
Summary: Retorna uma consulta simples dos dados da empresa informada.
Home-page: https://github.com/wherculano/Consulta-CNPJ
Author: Wagner Herculano
Author-email: wagherculano@hotmail.com
License: GNU AFFERO GENERAL PUBLIC LICENSE
Platform: UNKNOWN
Classifier: Development Status :: 2 - Pre-Alpha
Classifier: Environment :: Console
Classifier: Intended Audience :: Developers
Classifier: License :: OSI Approved :: GNU Affero General Public License v3 or later (AGPLv3+)
Classifier: Operating System :: OS Independent
Classifier: Programming Language :: Python
Classifier: Programming Language :: Python :: 3.6
Classifier: Framework :: Pytest
